{
  "attributes": {
    "minecraft:audio/background_music": {
      "default": {
        "max_delay": 24000,
        "min_delay": 12000,
        "sound": "minecraft:music.overworld.jungle"
      }
    },
    "minecraft:gameplay/increased_fire_burnout": true,
    "minecraft:visual/sky_color": 2525181,
    "minecraft:visual/fog_color": 9749759,
    "minecraft:audio/ambient_sounds": {
      "mood": {
        "sound": "minecraft:ambient.cave",
        "tick_delay": 6000,
        "block_search_extent": 8,
        "offset": 0
      }
    }
  },
  "carvers": [],
  "downfall": 0.9,
  "effects": {
    "water_color": 4159204,
    "grass_color": 4168459,
    "foliage_color": 6072580
  },
  "features": [],
  "has_precipitation": true,
  "spawn_costs": {},
  "spawners": {
    "ambient": [
      {
        "type": "minecraft:bat",
        "maxCount": 8,
        "minCount": 8,
        "weight": 10
      }
    ],
    "creature": [
      {
        "type": "minecraft:sheep",
        "maxCount": 4,
        "minCount": 4,
        "weight": 12
      },
      {
        "type": "minecraft:pig",
        "maxCount": 4,
        "minCount": 4,
        "weight": 10
      },
      {
        "type": "minecraft:chicken",
        "maxCount": 4,
        "minCount": 4,
        "weight": 10
      },
      {
        "type": "minecraft:cow",
        "maxCount": 4,
        "minCount": 4,
        "weight": 8
      },
      {
        "type": "minecraft:chicken",
        "maxCount": 4,
        "minCount": 4,
        "weight": 10
      },
      {
        "type": "minecraft:parrot",
        "maxCount": 2,
        "minCount": 1,
        "weight": 40
      },
      {
        "type": "minecraft:panda",
        "maxCount": 2,
        "minCount": 1,
        "weight": 1
      }
    ],
    "monster": [
      {
        "type": "minecraft:spider",
        "maxCount": 4,
        "minCount": 4,
        "weight": 100
      },
      {
        "type": "minecraft:zombie",
        "maxCount": 4,
        "minCount": 4,
        "weight": 95
      },
      {
        "type": "minecraft:zombie_villager",
        "maxCount": 1,
        "minCount": 1,
        "weight": 5
      },
      {
        "type": "minecraft:skeleton",
        "maxCount": 4,
        "minCount": 4,
        "weight": 100
      },
      {
        "type": "minecraft:creeper",
        "maxCount": 4,
        "minCount": 4,
        "weight": 100
      },
      {
        "type": "minecraft:slime",
        "maxCount": 4,
        "minCount": 4,
        "weight": 100
      },
      {
        "type": "minecraft:enderman",
        "maxCount": 4,
        "minCount": 1,
        "weight": 10
      },
      {
        "type": "minecraft:witch",
        "maxCount": 1,
        "minCount": 1,
        "weight": 5
      },
      {
        "type": "minecraft:ocelot",
        "maxCount": 3,
        "minCount": 1,
        "weight": 2
      }
    ],
    "underground_water_creature": [
      {
        "type": "minecraft:glow_squid",
        "maxCount": 6,
        "minCount": 4,
        "weight": 10
      }
    ]
  },
  "temperature": 0.95
}